[
 {
  "mascota": "Canino",
  "razas": "mediana",
  "categoria": "accesorios",
  "nombre": "asd",
  "tamaño": "asd",
  "cantidad": "1",
  "precio": "123",
  "imagen": "2.jpg"
 },
 {
  "nombre": "",
  "apellido": "",
  "correo": "",
  "contraseña": ""
 },
 {
  "nombre": "oswar ",
  "apellido": "baez",
  "correo": "oswar@gmail",
  "contraseña": "1234"
 },
 {
  "categoria": "accesorios",
  "nombre": "gggg",
  "tamaño": "gggg",
  "cantidad": "24",
  "precio": "1",
  "imagen": "cableado-electrico-defectuoso-inicio-incendio-caja-distribucion_351981-110.jpg"
 },
 {
  "nombre": "orlando",
  "apellido": "baez",
  "correo": "obaez@gmail.com",
  "contraseña": "0000"
 },
 {
  "nombre": "nuevo usuario",
  "apellido": "usuario nuevo",
  "correo": "usuer@gmail.com",
  "contraseña": "0000"
 },
 {
  "nombre": "User",
  "apellido": "baez",
  "correo": "user@gmail.com",
  "contraseña": "1234"
 },
 {
  "nombre": "",
  "apellido": "",
  "correo": "",
  "contraseña": ""
 },
 {
  "id": 9,
  "nombre": "loco",
  "apellido": "loco",
  "correo": "loco@gmail.com",
  "contraseña": "$2a$10$ikL7oCbWSpQl1OJcANTTxez4jpkGwP9Pf98whtHD/wZ77H2S8XRMu",
  "imagen": "imagen1644754668303.jpg"
 }
]